{
  "case": "Movilidad Urbana (Traffic)",
  "generated_at": "2026-02-09T20:24:47.853211Z",
  "git": {
    "commit": "0ea4bf874ef2200062def3c5acdd39093b25f7a0",
    "dirty": true
  },
  "phases": {
    "synthetic": {
      "phase": "synthetic",
      "overall_pass": false,
      "data": {
        "start": "2023-01-01 00:00:00",
        "end": "2023-01-07 23:00:00",
        "split": "2023-01-05 00:00:00",
        "obs_mean_raw": 30.715468474026746,
        "obs_std_raw": 51.277464279692865,
        "steps": 168,
        "val_steps": 72,
        "coverage": 168.0
      },
      "calibration": {
        "forcing_scale": 0.805220044232213,
        "macro_coupling": 0.07556904949216649,
        "ode_coupling_strength": 0.060455239593733195,
        "abm_feedback_gamma": 0.05,
        "damping": 0.10048108427017431,
        "ode_alpha": 0.2695108305890248,
        "ode_beta": 1.0,
        "assimilation_strength": 0.0,
        "calibration_rmse": 93.39908675647779,
        "ode_rolling": null
      },
      "forcing": {
        "driver_meta": null,
        "feedback_strength": 0.0,
        "feedback_used": false
      },
      "errors": {
        "rmse_abm": 33.88453964213964,
        "rmse_abm_no_ode": 34.66402278210417,
        "rmse_ode": 31.921465557958328,
        "rmse_reduced": 89.17020111241331,
        "threshold": 0.4997630744189651
      },
      "correlations": {
        "abm_obs": -0.010768348078715401,
        "ode_obs": -0.8516059465269133
      },
      "edi": {
        "value": 0.022486805552382288,
        "bootstrap_mean": 0.022043316832117927,
        "ci_lo": 0.00015956795224787224,
        "ci_hi": 0.04272984740178069,
        "valid": false,
        "weighted_value": 0.004497361110476458,
        "loe_factor": 0.2,
        "permutation_pvalue": 0.27,
        "permutation_null_95": 0.02261674878972472,
        "permutation_significant": false
      },
      "viscosity": {
        "pass": false,
        "detail": {
          "relaxation_time": 0,
          "peak_impact": 0.0
        }
      },
      "noise_sensitivity": {
        "stable": true,
        "cv": 0.0061238824126853796,
        "edi_mean": 0.635629757152144,
        "edi_std": 0.0038925218908034934,
        "monotonic_decrease": false
      },
      "effective_information": 0.0607879002069911,
      "symploke": {
        "internal": 0.0,
        "external": 0.0,
        "cr": 0.0,
        "pass": true,
        "cr_valid": false
      },
      "non_locality": {
        "dominance_share": 1.0,
        "pass": false
      },
      "persistence": {
        "model": 1.4166666666666667,
        "obs": 0.2110820971046824,
        "pass": true
      },
      "emergence": {
        "err_reduced": 34.66402278210417,
        "err_abm": 33.88453964213964,
        "threshold": 0.09995261488379303,
        "pass": true,
        "significance": "computed"
      },
      "coupling_check": false,
      "rmse_fraud_check": true,
      "c1_convergence": true,
      "c2_robustness": true,
      "c3_replication": false,
      "c4_validity": true,
      "c5_uncertainty": true,
      "c1_detail": {
        "rmse_abm": 33.88453964213964,
        "rmse_ode": 31.921465557958328,
        "corr_abm": -0.010768348078715401,
        "corr_ode": -0.8516059465269133,
        "threshold": 0.4997630744189651,
        "c1_relative": true,
        "c1_absolute": false,
        "rmse_reduced": 34.66402278210417,
        "relative_improvement": 0.7794831399645261
      },
      "c2_detail": {
        "mean_delta": 2.1916666666666678,
        "var_delta": 17.297569444444456,
        "relative_mean": 0.06924089512944277,
        "relative_var": 0.12284333777650532
      },
      "c3_detail": {
        "persistence_1": 1.4166666666666667,
        "persistence_2": 6.164930555555556
      },
      "c4_detail": {
        "diff": 7.125
      },
      "c5_detail": {
        "sensitivity_min": 27.36111111111111,
        "sensitivity_max": 34.59722222222222,
        "range": 7.236111111111111,
        "relative_range": 0.1411167890760306
      },
      "bias_correction": {
        "applied": false,
        "mode": "none",
        "ode_obs_corr_train": -0.3257385525113145,
        "ode_mean_train": null,
        "obs_mean_train": null,
        "scale_factor": null
      },
      "criteria": {
        "c1_convergence": true,
        "c1_relative": true,
        "c1_absolute": false,
        "c2_robustness": true,
        "c3_replication": false,
        "c4_validity": true,
        "c5_uncertainty": true,
        "symploke_pass": true,
        "non_locality_pass": false,
        "persistence_pass": true,
        "emergence_pass": true,
        "coupling_ok": false,
        "rmse_fraud_check": true,
        "edi_valid": false,
        "cr_valid": false
      },
      "emergence_taxonomy": {
        "category": "trend",
        "ode_quality": "good",
        "ode_obs_corr": -0.8516059465269133,
        "interpretation": "Tendencia no significativa: EDI positivo pero permutation test no lo confirma"
      },
      "synthetic_meta": {
        "mfd_true": {
          "vf": 60.0,
          "kj": 150.0
        }
      }
    },
    "real": {
      "phase": "real",
      "overall_pass": false,
      "data": {
        "start": "1970-01-01",
        "end": "2023-01-01",
        "split": "2005-01-01",
        "obs_mean_raw": 1706590976.9525623,
        "obs_std_raw": 1153379498.2622652,
        "steps": 53,
        "val_steps": 19,
        "coverage": 0.9814814814814815
      },
      "calibration": {
        "forcing_scale": 0.1433898023854741,
        "macro_coupling": 0.14510123805815683,
        "ode_coupling_strength": 0.11608099044652548,
        "abm_feedback_gamma": 0.05,
        "damping": 0.029094375366395628,
        "ode_alpha": 0.09098248373489348,
        "ode_beta": 0.7527563305433328,
        "assimilation_strength": 0.0,
        "calibration_rmse": 88.99722004415541,
        "ode_rolling": null
      },
      "forcing": {
        "driver_meta": {
          "cols": [
            "gdp_per_capita"
          ],
          "weights": [
            0.981301063664161
          ],
          "reg": 0.001
        },
        "feedback_strength": 0.0,
        "feedback_used": false
      },
      "errors": {
        "rmse_abm": 177.67067392343003,
        "rmse_abm_no_ode": 178.86194087943827,
        "rmse_ode": 9.9826532315147,
        "rmse_reduced": 85.8555048330392,
        "threshold": 1.8501359485304647
      },
      "correlations": {
        "abm_obs": 0.5974176290997641,
        "ode_obs": 0.1573583060555439
      },
      "edi": {
        "value": 0.00666025958429696,
        "bootstrap_mean": 0.0064676423878221685,
        "ci_lo": -0.005052300464938382,
        "ci_hi": 0.01911819572097914,
        "valid": false,
        "weighted_value": 0.0013320519168593921,
        "loe_factor": 0.2,
        "permutation_pvalue": 0.64,
        "permutation_null_95": 0.006790245276471191,
        "permutation_significant": false
      },
      "viscosity": {
        "pass": false,
        "detail": {
          "relaxation_time": 0,
          "peak_impact": 0.0
        }
      },
      "noise_sensitivity": {
        "stable": true,
        "cv": 0.02235323797052824,
        "edi_mean": -0.9761241192633004,
        "edi_std": 0.021819534726664844,
        "monotonic_decrease": false
      },
      "effective_information": -0.027978848837795667,
      "symploke": {
        "internal": 0.0,
        "external": 0.0,
        "cr": 0.0,
        "pass": true,
        "cr_valid": false
      },
      "non_locality": {
        "dominance_share": 1.0,
        "pass": false
      },
      "persistence": {
        "model": 430.1551246537396,
        "obs": 3.4230030280447226,
        "pass": false
      },
      "emergence": {
        "err_reduced": 178.86194087943827,
        "err_abm": 177.67067392343003,
        "threshold": 0.37002718970609294,
        "pass": true,
        "significance": "computed"
      },
      "coupling_check": true,
      "rmse_fraud_check": true,
      "c1_convergence": true,
      "c2_robustness": true,
      "c3_replication": false,
      "c4_validity": true,
      "c5_uncertainty": true,
      "c1_detail": {
        "rmse_abm": 177.67067392343003,
        "rmse_ode": 9.9826532315147,
        "corr_abm": 0.5974176290997641,
        "corr_ode": 0.1573583060555439,
        "threshold": 1.8501359485304647,
        "c1_relative": true,
        "c1_absolute": false,
        "rmse_reduced": 178.86194087943827,
        "relative_improvement": 1.191266956008235
      },
      "c2_detail": {
        "mean_delta": 3.410526315789474,
        "var_delta": 19.7229916897507,
        "relative_mean": 0.018837209302325582,
        "relative_var": 0.04585088159911391
      },
      "c3_detail": {
        "persistence_1": 430.1551246537396,
        "persistence_2": 412.4819944598338
      },
      "c4_detail": {
        "diff": 1.1052631578947398
      },
      "c5_detail": {
        "sensitivity_min": 154.31578947368422,
        "sensitivity_max": 187.26315789473685,
        "range": 32.94736842105263,
        "relative_range": 1.9305954892534544e-08
      },
      "bias_correction": {
        "applied": false,
        "mode": "none",
        "ode_obs_corr_train": 0.04968336076963678,
        "ode_mean_train": null,
        "obs_mean_train": null,
        "scale_factor": null
      },
      "criteria": {
        "c1_convergence": true,
        "c1_relative": true,
        "c1_absolute": false,
        "c2_robustness": true,
        "c3_replication": false,
        "c4_validity": true,
        "c5_uncertainty": true,
        "symploke_pass": true,
        "non_locality_pass": false,
        "persistence_pass": false,
        "emergence_pass": true,
        "coupling_ok": true,
        "rmse_fraud_check": true,
        "edi_valid": false,
        "cr_valid": false
      },
      "emergence_taxonomy": {
        "category": "trend",
        "ode_quality": "poor",
        "ode_obs_corr": 0.1573583060555439,
        "interpretation": "Tendencia no significativa: EDI positivo pero permutation test no lo confirma"
      },
      "gated_by_synthetic": true
    }
  }
}