{
  "case": "Justicia Algor\u00edtmica",
  "generated_at": "2026-02-07T14:28:34.774572Z",
  "git": {
    "commit": "7b9c9837f057bb3b5f3082a26dc9472277ae6e93",
    "dirty": true
  },
  "phases": {
    "synthetic": {
      "phase": "synthetic",
      "overall_pass": true,
      "data": {
        "start": "2005-01-01",
        "end": "2023-12-01",
        "split": "2016-01-01",
        "obs_mean_raw": 6.138652693521184,
        "obs_std_raw": 5.303576018986085,
        "steps": 228,
        "val_steps": 96,
        "coverage": 12.0
      },
      "calibration": {
        "forcing_scale": 0.37860808763750503,
        "macro_coupling": 0.5902557826629486,
        "damping": 0.5484045710477656,
        "ode_alpha": 0.019184413914737453,
        "ode_beta": 0.8209583816412064,
        "assimilation_strength": 0.0,
        "calibration_rmse": 0.14747764290853105
      },
      "errors": {
        "rmse_abm": 1.4225392203573957,
        "rmse_ode": 1.7844627895002998,
        "rmse_reduced": 5.219774284513116,
        "threshold": 1.708971526926005
      },
      "correlations": {
        "abm_obs": 0.9994649451567036,
        "ode_obs": 0.9998090325313221
      },
      "edi": {
        "value": 0.7274711236886202,
        "bootstrap_mean": 0.7276426977538952,
        "ci_lo": 0.7212837222186229,
        "ci_hi": 0.7344829965265152,
        "valid": true
      },
      "effective_information": 0.992862886003471,
      "symploke": {
        "internal": 0.9999979530416538,
        "external": 0.9996765299196135,
        "cr": 1.0003215271264458,
        "pass": true,
        "cr_valid": false
      },
      "non_locality": {
        "dominance_share": 0.002500002565692911,
        "pass": true
      },
      "persistence": {
        "model": 0.022015161604792114,
        "obs": 0.06344247984217578,
        "pass": true
      },
      "emergence": {
        "err_reduced": 5.219774284513116,
        "err_abm": 1.4225392203573957,
        "threshold": 0.34179430538520106,
        "pass": true,
        "significance": "computed"
      },
      "coupling_check": true,
      "rmse_fraud_check": true,
      "c1_convergence": true,
      "c2_robustness": true,
      "c3_replication": true,
      "c4_validity": true,
      "c5_uncertainty": true,
      "c1_detail": {
        "rmse_abm": 1.4225392203573957,
        "rmse_ode": 1.7844627895002998,
        "corr_abm": 0.9994649451567036,
        "corr_ode": 0.9998090325313221,
        "threshold": 1.708971526926005
      },
      "c2_detail": {
        "mean_delta": 0.26522771260614453,
        "var_delta": 0.17448290191239108,
        "relative_mean": 0.07246367079373912,
        "relative_var": 0.15141117926897044
      },
      "c3_detail": {
        "persistence_1": 0.022015161604792114,
        "persistence_2": 0.02201150573051804
      },
      "c4_detail": {
        "diff": 0.7320243479581467
      },
      "c5_detail": {
        "sensitivity_min": 3.0163804651404926,
        "sensitivity_max": 4.298542943465184,
        "range": 1.282162478324691,
        "relative_range": 0.20886708245897384
      },
      "synthetic_meta": {
        "ode_true": {
          "alpha": 0.08,
          "beta": 0.03
        },
        "measurement_noise": 0.05
      }
    },
    "real": {
      "phase": "real",
      "overall_pass": true,
      "data": {
        "start": "2005-01-01",
        "end": "2023-12-01",
        "split": "2016-01-01",
        "obs_mean_raw": 11.935337226575523,
        "obs_std_raw": 7.096679570195032,
        "steps": 228,
        "val_steps": 96,
        "coverage": 12.0
      },
      "calibration": {
        "forcing_scale": 0.6319732926446197,
        "macro_coupling": 0.5638900700145473,
        "damping": 0.95,
        "ode_alpha": 0.35318883392072736,
        "ode_beta": 1.0,
        "assimilation_strength": 0.0,
        "calibration_rmse": 0.15147438236132493
      },
      "errors": {
        "rmse_abm": 0.17095108477384752,
        "rmse_ode": 1.3871608009729421,
        "rmse_reduced": 3.1634275884533687,
        "threshold": 0.8069106870189338
      },
      "correlations": {
        "abm_obs": 0.9846149465840197,
        "ode_obs": 0.9849621204749293
      },
      "edi": {
        "value": 0.9459601713667082,
        "bootstrap_mean": 0.9458793639551134,
        "ci_lo": 0.93934810766413,
        "ci_hi": 0.9529533167476103,
        "valid": false
      },
      "effective_information": 1.2555109615769833,
      "symploke": {
        "internal": 0.9999732866348461,
        "external": 0.9999792047425318,
        "cr": 0.9999940817692432,
        "pass": true,
        "cr_valid": false
      },
      "non_locality": {
        "dominance_share": 0.0025000334877065154,
        "pass": true
      },
      "persistence": {
        "model": 0.01400485036263732,
        "obs": 0.0415546540771913,
        "pass": true
      },
      "emergence": {
        "err_reduced": 3.1634275884533687,
        "err_abm": 0.17095108477384752,
        "threshold": 0.16138213740378676,
        "pass": true,
        "significance": "computed"
      },
      "coupling_check": true,
      "rmse_fraud_check": true,
      "c1_convergence": true,
      "c2_robustness": true,
      "c3_replication": true,
      "c4_validity": true,
      "c5_uncertainty": true,
      "c1_detail": {
        "rmse_abm": 0.17095108477384752,
        "rmse_ode": 1.3871608009729421,
        "corr_abm": 0.9846149465840197,
        "corr_ode": 0.9849621204749293,
        "threshold": 0.8069106870189338
      },
      "c2_detail": {
        "mean_delta": 0.21737930245191733,
        "var_delta": 0.0840486987554788,
        "relative_mean": 0.07304074726092696,
        "relative_var": 0.0840486987554788
      },
      "c3_detail": {
        "persistence_1": 0.01400485036263732,
        "persistence_2": 0.014003032049245932
      },
      "c4_detail": {
        "diff": 0.5952249123429691
      },
      "c5_detail": {
        "sensitivity_min": 0.7144027624280317,
        "sensitivity_max": 3.498278305444645,
        "range": 2.7838755430166136,
        "relative_range": 0.23324649234191439
      }
    }
  }
}