{
  "case": "Wikipedia Clima",
  "generated_at": "2026-02-08T20:39:27.309670Z",
  "git": {
    "commit": "a8b288f4d7a0e4f7887f1d155b5dce4083b3cadb",
    "dirty": true
  },
  "phases": {
    "synthetic": {
      "phase": "synthetic",
      "overall_pass": false,
      "data": {
        "start": "2000-01-01",
        "end": "2019-12-01",
        "split": "2010-01-01",
        "obs_mean_raw": 1.394534426431708,
        "obs_std_raw": 0.5751853999231237,
        "steps": 240,
        "val_steps": 120,
        "coverage": 12.0
      },
      "calibration": {
        "forcing_scale": 0.6239682048315436,
        "macro_coupling": 0.1,
        "damping": 0.95,
        "ode_alpha": 0.06322627592583832,
        "ode_beta": 1.0,
        "assimilation_strength": 0.0,
        "calibration_rmse": 0.2459169602317246
      },
      "errors": {
        "rmse_abm": 1.0063564930551399,
        "rmse_abm_no_ode": 1.0174817206204612,
        "rmse_ode": 1.2829765522859395,
        "rmse_reduced": 1.6903559899930976,
        "threshold": 0.30465605623566305
      },
      "correlations": {
        "abm_obs": 0.9389676317209871,
        "ode_obs": 0.9386414524616739
      },
      "edi": {
        "value": 0.010934081015762261,
        "bootstrap_mean": 0.010942011363570665,
        "ci_lo": 0.010689708385367374,
        "ci_hi": 0.011224731240806753,
        "valid": false,
        "weighted_value": 0.002186816203152452,
        "loe_factor": 0.2
      },
      "viscosity": {
        "pass": false,
        "detail": {
          "relaxation_time": 0,
          "peak_impact": 0.0
        }
      },
      "effective_information": 0.007021183358844496,
      "symploke": {
        "internal": 0.9999628035980282,
        "external": 0.9999798217037733,
        "cr": 0.9999829815508516,
        "pass": true,
        "cr_valid": false
      },
      "non_locality": {
        "dominance_share": 0.0025000471339494384,
        "pass": true
      },
      "persistence": {
        "model": 0.004006435414099213,
        "obs": 0.011752043852529205,
        "pass": true
      },
      "emergence": {
        "err_reduced": 1.0174817206204612,
        "err_abm": 1.0063564930551399,
        "threshold": 0.06093121124713261,
        "pass": false,
        "significance": "computed"
      },
      "coupling_check": true,
      "rmse_fraud_check": true,
      "c1_convergence": false,
      "c2_robustness": true,
      "c3_replication": true,
      "c4_validity": true,
      "c5_uncertainty": true,
      "c1_detail": {
        "rmse_abm": 1.0063564930551399,
        "rmse_ode": 1.2829765522859395,
        "corr_abm": 0.9389676317209871,
        "corr_ode": 0.9386414524616739,
        "threshold": 0.30465605623566305
      },
      "c2_detail": {
        "mean_delta": 0.19462166890564614,
        "var_delta": 0.0627948280092583,
        "relative_mean": 0.07483089990170244,
        "relative_var": 0.0627948280092583
      },
      "c3_detail": {
        "persistence_1": 0.004006435414099213,
        "persistence_2": 0.004007599483895968
      },
      "c4_detail": {
        "diff": 0.5196920335967699
      },
      "c5_detail": {
        "sensitivity_min": 2.1361247496552545,
        "sensitivity_max": 3.064396492688296,
        "range": 0.9282717430330414,
        "relative_range": 0.36766293439002623
      },
      "synthetic_meta": {
        "ode_true": {
          "alpha": 0.08,
          "beta": 0.03
        },
        "measurement_noise": 0.05
      }
    },
    "real": {
      "phase": "real",
      "overall_pass": false,
      "data": {
        "start": "2010-01-01",
        "end": "2024-12-01",
        "split": "2020-01-01",
        "obs_mean_raw": 13.071011462234763,
        "obs_std_raw": 0.6120147143616395,
        "steps": 114,
        "val_steps": 60,
        "coverage": 7.6
      },
      "calibration": {
        "forcing_scale": 0.4921598390289366,
        "macro_coupling": 0.7722642314661723,
        "damping": 0.95,
        "ode_alpha": 0.035784010402290005,
        "ode_beta": 1.0,
        "assimilation_strength": 0.0,
        "calibration_rmse": 0.9280645813161893
      },
      "errors": {
        "rmse_abm": 4.427033261378464,
        "rmse_abm_no_ode": 4.440996259882794,
        "rmse_ode": 3.944135759511399,
        "rmse_reduced": 3.8377104219996827,
        "threshold": 2.5160463950133094
      },
      "correlations": {
        "abm_obs": -0.6620192893186104,
        "ode_obs": -0.5899875534224122
      },
      "edi": {
        "value": 0.0031441139976771245,
        "bootstrap_mean": 0.0031726824313771385,
        "ci_lo": 0.0024157877151776822,
        "ci_hi": 0.004012806020047374,
        "valid": false,
        "weighted_value": 0.000628822799535425,
        "loe_factor": 0.2
      },
      "viscosity": {
        "pass": false,
        "detail": {
          "relaxation_time": 0,
          "peak_impact": 0.0
        }
      },
      "effective_information": 0.0025966434783870618,
      "symploke": {
        "internal": -0.9952999126213788,
        "external": 0.00026046966583768435,
        "cr": 3821.1739912992985,
        "pass": false,
        "cr_valid": true
      },
      "non_locality": {
        "dominance_share": 0.0025385742303729703,
        "pass": true
      },
      "persistence": {
        "model": 0.08598784972553619,
        "obs": 16.41761782780613,
        "pass": true
      },
      "emergence": {
        "err_reduced": 4.440996259882794,
        "err_abm": 4.427033261378464,
        "threshold": 0.5032092790026619,
        "pass": false,
        "significance": "computed"
      },
      "coupling_check": true,
      "rmse_fraud_check": true,
      "c1_convergence": false,
      "c2_robustness": false,
      "c3_replication": false,
      "c4_validity": true,
      "c5_uncertainty": false,
      "c1_detail": {
        "rmse_abm": 4.427033261378464,
        "rmse_ode": 3.944135759511399,
        "corr_abm": -0.6620192893186104,
        "corr_ode": -0.5899875534224122,
        "threshold": 2.5160463950133094
      },
      "c2_detail": {
        "mean_delta": 9.674907223748729,
        "var_delta": 157766.0167740364,
        "relative_mean": 9.674907223748729,
        "relative_var": 157766.0167740364
      },
      "c3_detail": {
        "persistence_1": 0.08598784972553619,
        "persistence_2": 0.7410863973021575
      },
      "c4_detail": {
        "diff": 0.08805565059238696
      },
      "c5_detail": {
        "sensitivity_min": -5430.926345773659,
        "sensitivity_max": 26638.888383261736,
        "range": 32069.814729035395,
        "relative_range": 7.555286477469565
      }
    }
  }
}