{
  "case": "S\u00edndrome de Kessler",
  "generated_at": "2026-02-07T08:57:26.691702Z",
  "git": {
    "commit": "7b9c9837f057bb3b5f3082a26dc9472277ae6e93",
    "dirty": true
  },
  "phases": {
    "synthetic": {
      "phase": "synthetic",
      "overall_pass": false,
      "data": {
        "start": "1970-01-01",
        "end": "2019-01-01",
        "split": "2005-01-01",
        "obs_mean_raw": 0.17561444324369002,
        "obs_std_raw": 0.12894454706804725,
        "steps": 50,
        "val_steps": 15,
        "coverage": 1.0
      },
      "calibration": {
        "forcing_scale": 0.615975538420127,
        "macro_coupling": 0.37939537053108946,
        "damping": 0.95,
        "ode_alpha": 0.38163085587474493,
        "ode_beta": 1.0,
        "assimilation_strength": 0.0,
        "calibration_rmse": 0.5680609194333245
      },
      "errors": {
        "rmse_abm": 0.766270879243791,
        "rmse_ode": 0.7424334414796218,
        "rmse_reduced": 2.5531428909211815,
        "threshold": 0.706831423332583
      },
      "correlations": {
        "abm_obs": 0.4032653368442038,
        "ode_obs": 0.3195578776171259
      },
      "edi": {
        "value": 0.6998715262006671,
        "bootstrap_mean": 0.7070689104727013,
        "ci_lo": 0.6261292683557359,
        "ci_hi": 0.788661043409084,
        "valid": true
      },
      "effective_information": 0.05368214785953662,
      "symploke": {
        "internal": 0.9999260008228888,
        "external": 0.9998722811379561,
        "cr": 1.0000537265468261,
        "pass": true,
        "cr_valid": false
      },
      "non_locality": {
        "dominance_share": 0.0016000645500116482,
        "pass": true
      },
      "persistence": {
        "model": 0.06299310304419853,
        "obs": 0.6317782382721958,
        "pass": true
      },
      "emergence": {
        "err_reduced": 2.5531428909211815,
        "err_abm": 0.766270879243791,
        "threshold": 0.1413662846665166,
        "pass": true,
        "significance": "computed"
      },
      "coupling_check": true,
      "rmse_fraud_check": true,
      "c1_convergence": false,
      "c2_robustness": true,
      "c3_replication": true,
      "c4_validity": true,
      "c5_uncertainty": true,
      "c1_detail": {
        "rmse_abm": 0.766270879243791,
        "rmse_ode": 0.7424334414796218,
        "corr_abm": 0.4032653368442038,
        "corr_ode": 0.3195578776171259,
        "threshold": 0.706831423332583
      },
      "c2_detail": {
        "mean_delta": 0.1453753176809273,
        "var_delta": 0.01615623316435954,
        "relative_mean": 0.07084027866488062,
        "relative_var": 0.01615623316435954
      },
      "c3_detail": {
        "persistence_1": 0.06299310304419853,
        "persistence_2": 0.0629824204237942
      },
      "c4_detail": {
        "diff": 0.4104265110656775
      },
      "c5_detail": {
        "sensitivity_min": 1.695389573153593,
        "sensitivity_max": 2.4042049892738335,
        "range": 0.7088154161202405,
        "relative_range": 0.3552124106262582
      },
      "synthetic_meta": {
        "ode_true": {
          "alpha": 0.08,
          "beta": 0.03
        },
        "measurement_noise": 0.05
      }
    },
    "real": {
      "phase": "real",
      "overall_pass": true,
      "data": {
        "start": "1970-01-01",
        "end": "2019-01-01",
        "split": "2005-01-01",
        "obs_mean_raw": 19524620.53878631,
        "obs_std_raw": 8928116.615117041,
        "steps": 49,
        "val_steps": 15,
        "coverage": 0.98
      },
      "calibration": {
        "forcing_scale": 0.4712913093720783,
        "macro_coupling": 0.541562151621521,
        "damping": 0.6568914397548798,
        "ode_alpha": 0.09560941042750677,
        "ode_beta": 1.0,
        "assimilation_strength": 0.0,
        "calibration_rmse": 0.17430987477431198
      },
      "errors": {
        "rmse_abm": 0.8421062887944005,
        "rmse_ode": 0.8779211997792193,
        "rmse_reduced": 3.7653941952011607,
        "threshold": 1.0029447727461678
      },
      "correlations": {
        "abm_obs": 0.9847870934317513,
        "ode_obs": 0.9841690820118693
      },
      "edi": {
        "value": 0.7763564064905527,
        "bootstrap_mean": 0.7770755508202709,
        "ci_lo": 0.7632834617982861,
        "ci_hi": 0.7965110702020025,
        "valid": true
      },
      "effective_information": 1.001807325702204,
      "symploke": {
        "internal": 0.999979610815621,
        "external": 0.9986568128944471,
        "cr": 1.0013245770760228,
        "pass": true,
        "cr_valid": false
      },
      "non_locality": {
        "dominance_share": 0.001600017344444847,
        "pass": true
      },
      "persistence": {
        "model": 0.04763178174338596,
        "obs": 0.09966531624090287,
        "pass": true
      },
      "emergence": {
        "err_reduced": 3.7653941952011607,
        "err_abm": 0.8421062887944005,
        "threshold": 0.20058895454923356,
        "pass": true,
        "significance": "computed"
      },
      "coupling_check": true,
      "rmse_fraud_check": true,
      "c1_convergence": true,
      "c2_robustness": true,
      "c3_replication": true,
      "c4_validity": true,
      "c5_uncertainty": true,
      "c1_detail": {
        "rmse_abm": 0.8421062887944005,
        "rmse_ode": 0.8779211997792193,
        "corr_abm": 0.9847870934317513,
        "corr_ode": 0.9841690820118693,
        "threshold": 1.0029447727461678
      },
      "c2_detail": {
        "mean_delta": 0.19809919274597823,
        "var_delta": 0.0644383326933177,
        "relative_mean": 0.06888733822512462,
        "relative_var": 0.0644383326933177
      },
      "c3_detail": {
        "persistence_1": 0.04763178174338596,
        "persistence_2": 0.04763876012256426
      },
      "c4_detail": {
        "diff": 0.5751346158526447
      },
      "c5_detail": {
        "sensitivity_min": 2.382774663947991,
        "sensitivity_max": 3.359105477786937,
        "range": 0.9763308138389459,
        "relative_range": 0.3488861442154249
      }
    }
  }
}