{
  "case": "Micropl\u00e1sticos Oce\u00e1nicos (Jambeck Persistent Accumulation)",
  "generated_at": "2026-02-09T01:56:40.032633Z",
  "git": {
    "commit": "2ad9b5ae1eee32f909034b9ef002e96fa691c274",
    "dirty": true
  },
  "phases": {
    "synthetic": {
      "phase": "synthetic",
      "overall_pass": false,
      "data": {
        "start": "1980-01-01",
        "end": "2020-12-01",
        "split": "2002-01-01",
        "obs_mean_raw": 9.02055942238231,
        "obs_std_raw": 5.231829115269175,
        "steps": 492,
        "val_steps": 228,
        "coverage": 12.0
      },
      "calibration": {
        "forcing_scale": 0.7010641114725678,
        "macro_coupling": 0.41358692711426476,
        "damping": 0.6962833580181887,
        "ode_alpha": 0.016322429951996766,
        "ode_beta": 1.0,
        "assimilation_strength": 0.0,
        "calibration_rmse": 0.04167771225844066
      },
      "forcing": {
        "driver_meta": null,
        "feedback_strength": 0.0,
        "feedback_used": false
      },
      "errors": {
        "rmse_abm": 1.8557777481373712,
        "rmse_abm_no_ode": 0.3659487460042614,
        "rmse_ode": 5.198704899233553,
        "rmse_reduced": 3.0107938428306786,
        "threshold": 0.4661286036565238
      },
      "correlations": {
        "abm_obs": 0.8643570242921687,
        "ode_obs": 0.8659773882870936
      },
      "edi": {
        "value": -4.0711411595211775,
        "bootstrap_mean": -4.0650003374491375,
        "ci_lo": -4.483362979065898,
        "ci_hi": -3.6339373046417154,
        "valid": false,
        "weighted_value": -3.256912927616942,
        "loe_factor": 0.8
      },
      "viscosity": {
        "pass": true,
        "detail": {
          "relaxation_time": 2,
          "peak_impact": 2.0,
          "shock_step": 378,
          "recovered": true
        }
      },
      "effective_information": -0.6752806662487133,
      "symploke": {
        "internal": 0.9999949274959162,
        "external": 0.996430236123646,
        "cr": 1.0035774620671265,
        "pass": true,
        "cr_valid": false
      },
      "non_locality": {
        "dominance_share": 0.0016000351973060871,
        "pass": true
      },
      "persistence": {
        "model": 0.002263745433632997,
        "obs": 0.0003730873802569431,
        "pass": true
      },
      "emergence": {
        "err_reduced": 0.3659487460042614,
        "err_abm": 1.8557777481373712,
        "threshold": 0.09322572073130476,
        "pass": false,
        "significance": "computed"
      },
      "coupling_check": true,
      "rmse_fraud_check": true,
      "c1_convergence": false,
      "c2_robustness": true,
      "c3_replication": true,
      "c4_validity": true,
      "c5_uncertainty": true,
      "c1_detail": {
        "rmse_abm": 1.8557777481373712,
        "rmse_ode": 5.198704899233553,
        "corr_abm": 0.8643570242921687,
        "corr_ode": 0.8659773882870936,
        "threshold": 0.4661286036565238
      },
      "c2_detail": {
        "mean_delta": 0.18414597708550087,
        "var_delta": 0.08073046336502832,
        "relative_mean": 0.03907620859379846,
        "relative_var": 0.07917051525247917
      },
      "c3_detail": {
        "persistence_1": 0.002263745433632997,
        "persistence_2": 0.002262066076655243
      },
      "c4_detail": {
        "diff": 0.3461661761649504
      },
      "c5_detail": {
        "sensitivity_min": 4.188207902716673,
        "sensitivity_max": 5.210797404292651,
        "range": 1.022589501575978,
        "relative_range": 0.11336209360127629
      },
      "synthetic_meta": {
        "ode_true": {
          "inflow": 0.09,
          "decay": 0.003
        },
        "measurement_noise": 0.06
      }
    },
    "real": {
      "phase": "real",
      "overall_pass": false,
      "data": {
        "start": "1980-01-01",
        "end": "2020-12-01",
        "split": "2002-01-01",
        "obs_mean_raw": 220397591.025,
        "obs_std_raw": 113979515.9872994,
        "steps": 40,
        "val_steps": 18,
        "coverage": 0.975609756097561
      },
      "calibration": {
        "forcing_scale": 0.7461189742891696,
        "macro_coupling": 1.0,
        "damping": 0.4275794638412652,
        "ode_alpha": 0.04435400067231075,
        "ode_beta": 0.01336652457075578,
        "assimilation_strength": 0.0,
        "calibration_rmse": 0.3875154862430891
      },
      "forcing": {
        "driver_meta": {
          "cols": [
            "mismanaged_waste",
            "river_discharge"
          ],
          "weights": [
            0.20283935954083296,
            0.8037402851830778
          ],
          "reg": 0.001
        },
        "feedback_strength": 0.0,
        "feedback_used": false
      },
      "errors": {
        "rmse_abm": 11.728193470688828,
        "rmse_abm_no_ode": 18.01733694310297,
        "rmse_ode": 7.773369752682397,
        "rmse_reduced": 4.5301157851840665,
        "threshold": 1.4632995721487803
      },
      "correlations": {
        "abm_obs": 0.9366529289882896,
        "ode_obs": 0.8276529510527276
      },
      "edi": {
        "value": 0.3490606570923692,
        "bootstrap_mean": 0.3462523827358279,
        "ci_lo": 0.26450344969564843,
        "ci_hi": 0.40614443972253794,
        "valid": true,
        "weighted_value": 0.2792485256738954,
        "loe_factor": 0.8
      },
      "viscosity": {
        "pass": true,
        "detail": {
          "relaxation_time": 4,
          "peak_impact": 2.0,
          "shock_step": 31,
          "recovered": true
        }
      },
      "effective_information": 0.6307048606332035,
      "symploke": {
        "internal": 0.9999681576373856,
        "external": 0.9884080483475922,
        "cr": 1.0116956851060848,
        "pass": true,
        "cr_valid": false
      },
      "non_locality": {
        "dominance_share": 0.0016001688675406885,
        "pass": true
      },
      "persistence": {
        "model": 10.797229065577042,
        "obs": 1.45645641091809,
        "pass": false
      },
      "emergence": {
        "err_reduced": 18.01733694310297,
        "err_abm": 11.728193470688828,
        "threshold": 0.2926599144297561,
        "pass": true,
        "significance": "computed"
      },
      "coupling_check": true,
      "rmse_fraud_check": true,
      "c1_convergence": false,
      "c2_robustness": true,
      "c3_replication": true,
      "c4_validity": true,
      "c5_uncertainty": true,
      "c1_detail": {
        "rmse_abm": 11.728193470688828,
        "rmse_ode": 7.773369752682397,
        "corr_abm": 0.9366529289882896,
        "corr_ode": 0.8276529510527276,
        "threshold": 1.4632995721487803
      },
      "c2_detail": {
        "mean_delta": 0.35048036870924654,
        "var_delta": 2.1079645273693375,
        "relative_mean": 0.02352500692657794,
        "relative_var": 0.05244143254032766
      },
      "c3_detail": {
        "persistence_1": 10.797229065577042,
        "persistence_2": 10.79739293104132
      },
      "c4_detail": {
        "diff": 1.3967289414209567
      },
      "c5_detail": {
        "sensitivity_min": 13.932621499126917,
        "sensitivity_max": 15.818695286762669,
        "range": 1.8860737876357518,
        "relative_range": 8.557597108317812e-09
      }
    }
  }
}